xsquared/__init__.py
xsquared-1.0.1.dist-info/METADATA
xsquared-1.0.1.dist-info/WHEEL
xsquared-1.0.1.dist-info/top_level.txt
xsquared-1.0.1.dist-info/RECORD
